Mix50/__init__.py
Mix50/effects.py
Mix50/features.py
Mix50/mixfifty.py
Mix50/process.py
Mix50/transitions.py
Mix50-0.5.dist-info/LICENSE
Mix50-0.5.dist-info/METADATA
Mix50-0.5.dist-info/WHEEL
Mix50-0.5.dist-info/top_level.txt
Mix50-0.5.dist-info/RECORD
